vaxpress/__init__.py
vaxpress/__main__.py
vaxpress/config.py
vaxpress/datacache.py
vaxpress/evolution_chamber.py
vaxpress/lineardesign.py
vaxpress/log.py
vaxpress/mutant_generator.py
vaxpress/presets.py
vaxpress/reporting.py
vaxpress/sequence_evaluator.py
vaxpress/data/__init__.py
vaxpress/data/bicodon_usage_data.py
vaxpress/data/codon_usage_data.py
vaxpress/report_template/report.html
vaxpress/scoring/__init__.py
vaxpress/scoring/bicodon.py
vaxpress/scoring/cai.py
vaxpress/scoring/degscore.py
vaxpress/scoring/gc_ratio.py
vaxpress/scoring/icodon_stability.py
vaxpress/scoring/long_stems.py
vaxpress/scoring/loops.py
vaxpress/scoring/mfe.py
vaxpress/scoring/start_structure.py
vaxpress/scoring/tandem_repeats.py
vaxpress/scoring/ucount.py
vaxpress-0.9.data/data/share/vaxpress/examples/adenosine_in_stems.py
vaxpress-0.9.data/data/share/vaxpress/examples/count_homotrimers.py
vaxpress-0.9.data/data/share/vaxpress/examples/restriction_site.py
vaxpress-0.9.dist-info/LICENSE.txt
vaxpress-0.9.dist-info/METADATA
vaxpress-0.9.dist-info/WHEEL
vaxpress-0.9.dist-info/entry_points.txt
vaxpress-0.9.dist-info/top_level.txt
vaxpress-0.9.dist-info/RECORD
