Metadata-Version: 2.1
Name: vaxpress
Version: 0.9
Summary: Codon Optimizer for mRNA Vaccine Design
Home-page: https://github.com/ChangLabSNU/VaxPress
Download-URL: https://github.com/ChangLabSNU/VaxPress/releases
Author: Hyeshik Chang
Author-email: hyeshik@snu.ac.kr
License: MIT
Keywords: mRNA vaccine,messenger RNA,codon optimization
Classifier: Development Status :: 3 - Alpha
Classifier: Environment :: Console
Classifier: Intended Audience :: Healthcare Industry
Classifier: Intended Audience :: Science/Research
Classifier: License :: OSI Approved :: MIT License
Classifier: Operating System :: POSIX
Classifier: Programming Language :: Python :: 3 :: Only
Classifier: Topic :: Scientific/Engineering :: Bio-Informatics
License-File: LICENSE.txt
Requires-Dist: biopython >=1.5
Requires-Dist: numpy >=1.15
Requires-Dist: pandas >=2.0
Requires-Dist: pytrf >=1.0.1
Requires-Dist: ViennaRNA >=2.4
Requires-Dist: tqdm >=4.0
Requires-Dist: tabulate >=0.9
Requires-Dist: Jinja2 >=3.1
Requires-Dist: plotly >=5.0
Requires-Dist: pylru >=1.2
Provides-Extra: nonfree
Requires-Dist: linearfold-unofficial ; extra == 'nonfree'
